01_combinational_logic/01_07_mux_using_narrow_data_muxes/01_07_mux_using_narrow_data_muxes.sv
//----------------------------------------------------------------------------
// Example
//----------------------------------------------------------------------------

module mux_4_1_width_2
(
  input  [1:0] d0, d1, d2, d3,
  input  [1:0] sel,
  output [1:0] y
);

  assign y = sel [1] ? (sel [0] ? d3 : d2)
                     : (sel [0] ? d1 : d0);

endmodule

//----------------------------------------------------------------------------
// Task
//----------------------------------------------------------------------------

module mux_4_1
(
  input  [3:0] d0, d1, d2, d3,
  input  [1:0] sel,
  output [3:0] y
);

  // Task:
  // Implement mux_4_1 with 4-bit data
  // using two instances of mux_4_1_width_2 with 2-bit data

  mux_4_1_width_2 inst1(
    .d0(d0[3:2]),
    .d1(d1[3:2]),
    .d2(d2[3:2]),
    .d3(d3[3:2]),
    .sel(sel),
    .y(y[3:2])
  );

  mux_4_1_width_2 inst2(
    .d0(d0[1:0]),
    .d1(d1[1:0]),
    .d2(d2[1:0]),
    .d3(d3[1:0]),
    .sel(sel),
    .y(y[1:0])
  );


endmodule

01_combinational_logic/01_01_mux_question/testbench.sv
`include "util.svh"

module testbench;

  logic [3:0] d0, d1, d2, d3;
  logic [1:0] sel;
  logic [3:0] y;

  mux_4_1 inst
  (
    .d0  (d0), .d1 (d1), .d2 (d2), .d3 (d3),
    .sel (sel),
    .y   (y)
  );

  task test
    (
      input [3:0] td0, td1, td2, td3,
      input [1:0] tsel,
      input [3:0] ty
    );

    { d0, d1, d2, d3, sel } = { td0, td1, td2, td3, tsel };

    # 1;

    if (y !== ty)
      begin
        $display("FAIL %s", `__FILE__);
        $display("++ INPUT    => {%s, %s, %s, %s, %s}", `PH(d0), `PH(d1), `PH(d2), `PH(d3), `PH(sel));
        $display("++ EXPECTED => {%s}", `PH(ty));
        $display("++ ACTUAL   => {%s}", `PH(y));
        $finish(1);
      end

  endtask

  initial
    begin
    $dumpfile("out.vcd");
    $dumpvars(0, testbench);
      test ('ha, 'hb, 'hc, 'hd, 0, 'ha);
      test ('ha, 'hb, 'hc, 'hd, 1, 'hb);
      test ('ha, 'hb, 'hc, 'hd, 2, 'hc);
      test ('ha, 'hb, 'hc, 'hd, 3, 'hd);

      test (7, 10, 3, 'x, 0, 7);
      test (7, 10, 3, 'x, 1, 10);
      test (7, 10, 3, 'x, 2, 3);
      test (7, 10, 3, 'x, 3, 'x);

      $display ("PASS %s", `__FILE__);
      $finish;
    end

endmodule

01_combinational_logic/out.vcd
$date
	Sun Apr 13 15:40:16 2025
$end
$version
	Icarus Verilog
$end
$timescale
	1s
$end
$scope module testbench $end
$var wire 4 ! y [3:0] $end
$var reg 4 " d0 [3:0] $end
$var reg 4 # d1 [3:0] $end
$var reg 4 $ d2 [3:0] $end
$var reg 4 % d3 [3:0] $end
$var reg 2 & sel [1:0] $end
$scope module inst $end
$var wire 4 ' d0 [3:0] $end
$var wire 4 ( d1 [3:0] $end
$var wire 4 ) d2 [3:0] $end
$var wire 4 * d3 [3:0] $end
$var wire 2 + sel [1:0] $end
$var wire 4 , y [3:0] $end
$upscope $end
$scope task test $end
$var reg 4 - td0 [3:0] $end
$var reg 4 . td1 [3:0] $end
$var reg 4 / td2 [3:0] $end
$var reg 4 0 td3 [3:0] $end
$var reg 2 1 tsel [1:0] $end
$var reg 4 2 ty [3:0] $end
$upscope $end
$upscope $end
$enddefinitions $end
#0
$dumpvars
b1010 2
b0 1
b1101 0
b1100 /
b1011 .
b1010 -
b1010 ,
b0 +
b1101 *
b1100 )
b1011 (
b1010 '
b0 &
b1101 %
b1100 $
b1011 #
b1010 "
b1010 !
$end
#1
b1011 !
b1011 ,
b1 &
b1 +
b1011 2
b1 1
#2
b1100 !
b1100 ,
b10 &
b10 +
b1100 2
b10 1
#3
b1101 !
b1101 ,
b11 &
b11 +
b1101 2
b11 1
#4
b111 !
b111 ,
b111 "
b111 '
b1010 #
b1010 (
b11 $
b11 )
bx %
bx *
b0 &
b0 +
b111 2
b0 1
bx 0
b11 /
b1010 .
b111 -
#5
b1010 !
b1010 ,
b1 &
b1 +
b1010 2
b1 1
#6
b11 !
b11 ,
b10 &
b10 +
b11 2
b10 1
#7
bx !
bx ,
b11 &
b11 +
bx 2
b11 1
